{
"entidad_principal": "Recurso administrativo",
"entidad_normalizada": "Recurso administrativo",
"tipo_entidad": "otro",
"accion": "recurso",
"es_ma": false,
"contraparte": null,
"contraparte_normalizada": null,
"porcentaje": null,
"monto_valor": null,
"monto_moneda": null,
"resultado": "recurso con lugar",
"resumen": "Recurso administrativo: recurso con lugar",
"relevancia": "baja",
"_motor": "heuristica",
"id": "RR-SSF-2019-569",
"year": "2019",
"month": "Agosto",
"month_num": 8,
"number": "569",
"title": "RECURSOS DE REVOCACIÓN Y JERÁRQUICO EN SUBSIDIO - ACTO ADMINISTRATIVO REGLAMENTARIO COMUNICADO POR CIRCULAR N° 2320. No se hace lugar",
"url": "https://www.bcu.gub.uy/Servicios-Financieros-SSF/Resoluciones_SSF/RR-SSF-2019-569.pdf",
"sort": 201900569
}