{
"entidad_principal": "BANCO ITAÚ URUGUAY S.A.",
"entidad_normalizada": "Itaú",
"tipo_entidad": "banco",
"accion": "inscripcion",
"es_ma": false,
"contraparte": null,
"contraparte_normalizada": null,
"porcentaje": null,
"monto_valor": null,
"monto_moneda": null,
"resultado": "inscripción aprobada",
"resumen": "Itaú: inscripción aprobada",
"relevancia": "media",
"_motor": "heuristica",
"id": "RR-SSF-2023-203",
"year": "2023",
"month": "Abril",
"month_num": 4,
"number": "203",
"title": "BANCO ITAÚ URUGUAY S.A. - FONDOS DE INVERSIÓN DEL EXTERIOR EN RÉGIMEN DE OFERTA PÚBLICA A DISTRIBUIR, ADMINISTRADOS POR NORDEA INVESTMENT FUNDS S.A. Inscripción",
"url": "https://www.bcu.gub.uy/Servicios-Financieros-SSF/Resoluciones_SSF/RR-SSF-2023-203.pdf",
"sort": 202300203
}