{
"entidad_principal": "REQUERIMIENTO DE CAPITAL CONTRACÍCLICO",
"entidad_normalizada": "REQUERIMIENTO DE CAPITAL CONTRACÍCLICO",
"tipo_entidad": "otro",
"accion": "normativa",
"es_ma": false,
"contraparte": null,
"contraparte_normalizada": null,
"porcentaje": null,
"monto_valor": null,
"monto_moneda": null,
"resultado": "normativa emitida",
"resumen": "REQUERIMIENTO DE CAPITAL CONTRACÍCLICO: normativa emitida",
"relevancia": "baja",
"_motor": "heuristica",
"id": "RR-SSF-2022-408",
"year": "2022",
"month": "Junio",
"month_num": 6,
"number": "408",
"title": "REQUERIMIENTO DE CAPITAL CONTRACÍCLICO – ARTÍCULO 158.2 DE LA RECOPILACIÓN DE NORMAS DE REGULACIÓN Y CONTROL DEL SISTEMA FINANCIERO. Establecer porcentaje",
"url": "https://www.bcu.gub.uy/Servicios-Financieros-SSF/Resoluciones_SSF/RR-SSF-2022-408.pdf",
"sort": 202200408
}