{
"entidad_principal": "COOPERATIVA POLICIAL DE AHORRO Y CREDITO “CO.P.A.C.”",
"entidad_normalizada": "COOPERATIVA POLICIAL DE AHORRO Y CREDITO “CO.P.A.C",
"tipo_entidad": "cooperativa",
"accion": "inscripcion",
"es_ma": false,
"contraparte": null,
"contraparte_normalizada": null,
"porcentaje": null,
"monto_valor": null,
"monto_moneda": null,
"resultado": "inscripción aprobada",
"resumen": "COOPERATIVA POLICIAL DE AHORRO Y CREDITO “CO.P.A.C: inscripción aprobada",
"relevancia": "media",
"_motor": "heuristica",
"id": "RR-SSF-2024-275",
"year": "2024",
"month": "Junio",
"month_num": 6,
"number": "275",
"title": "COOPERATIVA POLICIAL DE AHORRO Y CREDITO “CO.P.A.C.” - SOLICITUD DE INSCRIPCIÓN EN EL REGISTRO DE ENTIDADES OTORGANTES DE CRÉDITO DE MAYOR ACTIVIDAD. Inscripción",
"url": "https://www.bcu.gub.uy/Servicios-Financieros-SSF/Resoluciones_SSF/RR-SSF-2024-275.pdf",
"sort": 202400275
}