{
"entidad_principal": "AVENIDA SA EMPRESA DE SERVICIOS FINANCIEROS",
"entidad_normalizada": "AVENIDA EMPRESA DE SERVICIOS FINANCIEROS",
"tipo_entidad": "otro",
"accion": "multa",
"es_ma": false,
"contraparte": null,
"contraparte_normalizada": null,
"porcentaje": null,
"monto_valor": null,
"monto_moneda": null,
"resultado": "sancionado con multa",
"resumen": "AVENIDA EMPRESA DE SERVICIOS FINANCIEROS: sancionado con multa",
"relevancia": "media",
"_motor": "heuristica",
"id": "RR-SSF-2019-842",
"year": "2019",
"month": "Diciembre",
"month_num": 12,
"number": "842",
"title": "AVENIDA SA EMPRESA DE SERVICIOS FINANCIEROS - SOLICITUD EXONERACION DE MULTA . Autorización",
"url": "https://www.bcu.gub.uy/Servicios-Financieros-SSF/Resoluciones_SSF/RR-SSF-2019-842.pdf",
"sort": 201900842
}