{
"entidad_principal": "REPÚBLICA ADMINISTRADORA DE FONDOS DE INVERSIÓN S.A.",
"entidad_normalizada": "REPÚBLICA ADMINISTRADORA DE FONDOS DE INVERSIÓN",
"tipo_entidad": "fondo",
"accion": "otro",
"es_ma": false,
"contraparte": null,
"contraparte_normalizada": null,
"porcentaje": null,
"monto_valor": null,
"monto_moneda": null,
"resultado": "",
"resumen": "REPÚBLICA ADMINISTRADORA DE FONDOS DE INVERSIÓN: otro",
"relevancia": "media",
"_motor": "heuristica",
"id": "RR-SSF-2023-95",
"year": "2023",
"month": "Febrero",
"month_num": 2,
"number": "95",
"title": "REPÚBLICA ADMINISTRADORA DE FONDOS DE INVERSIÓN S.A. - MODIFICACIÓN DEL CONTRATO DE \"FIDEICOMISO FINANCIERO PARA PLANES Y PROGRAMAS DE VIVIENDA DE MALDONADO\". Estampar constancia",
"url": "https://www.bcu.gub.uy/Servicios-Financieros-SSF/Resoluciones_SSF/RR-SSF-2023-95.pdf",
"sort": 202300095
}