{
"entidad_principal": "BOLSA DE VALORES DE MONTEVIDEO S.A.- SOLICITA HABILITACIÓN",
"entidad_normalizada": "BOLSA DE VALORES DE MONTEVIDEO .- SOLICITA HABILIT",
"tipo_entidad": "emisor_valores",
"accion": "inscripcion",
"es_ma": false,
"contraparte": null,
"contraparte_normalizada": null,
"porcentaje": null,
"monto_valor": null,
"monto_moneda": null,
"resultado": "inscripción aprobada",
"resumen": "BOLSA DE VALORES DE MONTEVIDEO .- SOLICITA HABILIT: inscripción aprobada",
"relevancia": "media",
"_motor": "heuristica",
"id": "RR-SSF-2020-419",
"year": "2020",
"month": "Julio",
"month_num": 7,
"number": "419",
"title": "BOLSA DE VALORES DE MONTEVIDEO S.A.- SOLICITA HABILITACIÓN COMO ENTIDAD REGISTRANTE DE EMISIONES DE VALORES DE OFERTA PÚBLICA Y PRIVADA. Autorización",
"url": "https://www.bcu.gub.uy/Servicios-Financieros-SSF/Resoluciones_SSF/RR-SSF-2020-419.pdf",
"sort": 202000419
}