{
"entidad_principal": "ITAÚ ADMINISTRADORA DE FONDOS DE INVERSIÓN S.A.",
"entidad_normalizada": "Itaú",
"tipo_entidad": "fondo",
"accion": "otro",
"es_ma": false,
"contraparte": null,
"contraparte_normalizada": null,
"porcentaje": null,
"monto_valor": null,
"monto_moneda": null,
"resultado": "",
"resumen": "Itaú: otro",
"relevancia": "media",
"_motor": "heuristica",
"id": "RR-SSF-2023-539",
"year": "2023",
"month": "Octubre",
"month_num": 10,
"number": "539",
"title": "ITAÚ ADMINISTRADORA DE FONDOS DE INVERSIÓN S.A. - REGLAMENTO DEL FONDO DE INVERSIÓN DENOMINADO “ITAÚ LIQUIDEZ PESOS FONDO DE INVERSIÓN”. Aprobación",
"url": "https://www.bcu.gub.uy/Servicios-Financieros-SSF/Resoluciones_SSF/RR-SSF-2023-539.pdf",
"sort": 202300539
}