{
"entidad_principal": "GALIMIR S.A.",
"entidad_normalizada": "GALIMIR",
"tipo_entidad": "otro",
"accion": "otro",
"es_ma": false,
"contraparte": null,
"contraparte_normalizada": null,
"porcentaje": null,
"monto_valor": null,
"monto_moneda": null,
"resultado": "",
"resumen": "GALIMIR: otro",
"relevancia": "media",
"_motor": "heuristica",
"id": "RR-SSF-2024-150",
"year": "2024",
"month": "Marzo",
"month_num": 3,
"number": "150",
"title": "GALIMIR S.A. - NUEVOS ACCIONISTAS. No objeción",
"url": "https://www.bcu.gub.uy/Servicios-Financieros-SSF/Resoluciones_SSF/RR-SSF-2024-150.pdf",
"sort": 202400150
}