{
"entidad_principal": "BANCO BILBAO VIZCAYA ARGENTARIA URUGUAY S.A. (BBVA)",
"entidad_normalizada": "BBVA",
"tipo_entidad": "banco",
"accion": "otro",
"es_ma": false,
"contraparte": null,
"contraparte_normalizada": null,
"porcentaje": null,
"monto_valor": null,
"monto_moneda": null,
"resultado": "",
"resumen": "BBVA: otro",
"relevancia": "media",
"_motor": "heuristica",
"id": "RR-SSF-2022-141",
"year": "2022",
"month": "Marzo",
"month_num": 3,
"number": "141",
"title": "BANCO BILBAO VIZCAYA ARGENTARIA URUGUAY S.A. (BBVA) - RETRASO EN ACREDITACIÓN DE REINTEGROS A SU CUENTA. Denuncia de un particular",
"url": "https://www.bcu.gub.uy/Servicios-Financieros-SSF/Resoluciones_SSF/RR-SSF-2022-141.pdf",
"sort": 202200141
}