{
"entidad_principal": "BANCO ITAÚ URUGUAY S.A.",
"entidad_normalizada": "Itaú",
"tipo_entidad": "banco",
"accion": "sancion",
"es_ma": false,
"contraparte": null,
"contraparte_normalizada": null,
"porcentaje": null,
"monto_valor": null,
"monto_moneda": null,
"resultado": "sancionado",
"resumen": "Itaú: sancionado",
"relevancia": "media",
"_motor": "heuristica",
"id": "RR-SSF-2025-400",
"year": "2025",
"month": "Agosto",
"month_num": 8,
"number": "400",
"title": "BANCO ITAÚ URUGUAY S.A. - REGISTRO DE LA CENTRAL DE RIESGOS. SOLICITUD DE MODIFICACIÓN DEL PATRONÍMICO. Declarar que el interés del particular ha sido satisfecho y sanción",
"url": "https://www.bcu.gub.uy/Servicios-Financieros-SSF/Resoluciones_SSF/RR-SSF-2025-400.pdf",
"sort": 202500400
}