{
"entidad_principal": "PASS CARD S.A.",
"entidad_normalizada": "PASS CARD",
"tipo_entidad": "otro",
"accion": "sancion",
"es_ma": false,
"contraparte": null,
"contraparte_normalizada": null,
"porcentaje": null,
"monto_valor": null,
"monto_moneda": null,
"resultado": "sancionado",
"resumen": "PASS CARD: sancionado",
"relevancia": "media",
"_motor": "heuristica",
"id": "RR-SSF-2023-186",
"year": "2023",
"month": "Marzo",
"month_num": 3,
"number": "186",
"title": "PASS CARD S.A. - INCUMPLIMIENTO DE LO ESTABLECIDO EN LA LEY 18.212. Sanción",
"url": "https://www.bcu.gub.uy/Servicios-Financieros-SSF/Resoluciones_SSF/RR-SSF-2023-186.pdf",
"sort": 202300186
}