{
"entidad_principal": "AMURA ADVISORS SRL",
"entidad_normalizada": "AMURA ADVISORS",
"tipo_entidad": "asesor_inversion",
"accion": "inscripcion",
"es_ma": false,
"contraparte": null,
"contraparte_normalizada": null,
"porcentaje": null,
"monto_valor": null,
"monto_moneda": null,
"resultado": "inscripción aprobada",
"resumen": "AMURA ADVISORS: inscripción aprobada",
"relevancia": "media",
"_motor": "heuristica",
"id": "RR-SSF-2020-417",
"year": "2020",
"month": "Julio",
"month_num": 7,
"number": "417",
"title": "AMURA ADVISORS SRL - SOLICITA INSCRIPCIÓN COMO ASESOR DE INVERSIONES. Inscripción",
"url": "https://www.bcu.gub.uy/Servicios-Financieros-SSF/Resoluciones_SSF/RR-SSF-2020-417.pdf",
"sort": 202000417
}