{
"entidad_principal": "BEENOLL CORP S.A.",
"entidad_normalizada": "BEENOLL CORP",
"tipo_entidad": "casa_cambio",
"accion": "autorizacion",
"es_ma": false,
"contraparte": null,
"contraparte_normalizada": null,
"porcentaje": null,
"monto_valor": null,
"monto_moneda": null,
"resultado": "autorizado",
"resumen": "BEENOLL CORP: autorizado",
"relevancia": "media",
"_motor": "heuristica",
"id": "RR-SSF-2022-217",
"year": "2022",
"month": "Abril",
"month_num": 4,
"number": "217",
"title": "BEENOLL CORP S.A. - CAMBIO DE LICENCIA DE ASESOR DE INVERSIÓN A GESTOR DE PORTAFOLIOS Y TERCERIZACiÓN DE SERVICIOS. Autorización",
"url": "https://www.bcu.gub.uy/Servicios-Financieros-SSF/Resoluciones_SSF/RR-SSF-2022-217.pdf",
"sort": 202200217
}