{
"entidad_principal": "LLAMADO A INVERTIR O AHORRAR CON RENDIMIENTOS DETERMINADOS",
"entidad_normalizada": "LLAMADO A INVERTIR O AHORRAR CON RENDIMIENTOS DETE",
"tipo_entidad": "otro",
"accion": "inscripcion",
"es_ma": false,
"contraparte": null,
"contraparte_normalizada": null,
"porcentaje": null,
"monto_valor": null,
"monto_moneda": null,
"resultado": "inscripción aprobada",
"resumen": "LLAMADO A INVERTIR O AHORRAR CON RENDIMIENTOS DETE: inscripción aprobada",
"relevancia": "media",
"_motor": "heuristica",
"id": "RR-SSF-2022-166",
"year": "2022",
"month": "Marzo",
"month_num": 3,
"number": "166",
"title": "LLAMADO A INVERTIR O AHORRAR CON RENDIMIENTOS DETERMINADOS - ADVERTENCIA SOBRE ACTIVIDAD NO INSCRIPTA EN LA SSF. Emisión de Comunicación",
"url": "https://www.bcu.gub.uy/Servicios-Financieros-SSF/Resoluciones_SSF/RR-SSF-2022-166.pdf",
"sort": 202200166
}