{
"entidad_principal": "MOODY'S INVESTORS SERVICE INC",
"entidad_normalizada": "MOODY'S INVESTORS SERVICE INC",
"tipo_entidad": "otro",
"accion": "inscripcion",
"es_ma": false,
"contraparte": null,
"contraparte_normalizada": null,
"porcentaje": null,
"monto_valor": null,
"monto_moneda": null,
"resultado": "inscripción aprobada",
"resumen": "MOODY'S INVESTORS SERVICE INC: inscripción aprobada",
"relevancia": "media",
"_motor": "heuristica",
"id": "RR-SSF-2019-68",
"year": "2019",
"month": "Enero",
"month_num": 1,
"number": "68",
"title": "MOODY'S INVESTORS SERVICE INC - REGISTRO DE MERCADO DE VALORES. Inscripción",
"url": "https://www.bcu.gub.uy/Servicios-Financieros-SSF/Resoluciones_SSF/RR-SSF-2019-68.pdf",
"sort": 201900068
}